minidraw/__init__.py
minidraw/drawing.py
minidraw/point.py
minidraw/primitives.py
minidraw/spatial.py
minidraw/style.py
minidraw/transform.py
minidraw/backend/__init__.py
minidraw/backend/base.py
minidraw/backend/python.py
minidraw/backend/svg.py
minidraw-0.1.0.dist-info/METADATA
minidraw-0.1.0.dist-info/WHEEL
minidraw-0.1.0.dist-info/licenses/LICENSE.txt
minidraw-0.1.0.dist-info/RECORD
