Metadata-Version: 2.4
Name: minidraw
Version: 0.1.0
Summary: A minimal Python drawing library.
Project-URL: Homepage, https://github.com/liborw/minidraw
Project-URL: Repository, https://github.com/liborw/minidraw
Project-URL: Issues, https://github.com/liborw/minidraw/issues
Author: Libor Wagner
License: MIT
License-File: LICENSE.txt
Keywords: canvas,drawing,graphics,minimal,rendering,svg
Classifier: Development Status :: 3 - Alpha
Classifier: License :: OSI Approved :: MIT License
Classifier: Programming Language :: Python :: 3
Classifier: Programming Language :: Python :: 3.10
Classifier: Programming Language :: Python :: 3.11
Classifier: Topic :: Multimedia :: Graphics
Classifier: Topic :: Software Development :: Libraries
Requires-Python: >=3.9
Provides-Extra: dev
Requires-Dist: mypy>=1.10; extra == 'dev'
Requires-Dist: ruff>=0.6; extra == 'dev'
